HiveToClickhouse
