Metadata-Version: 1.0
Name: HiveToClickhouse
Version: 1.0.5
Summary: hive sql 转clickhouse sql
Home-page: UNKNOWN
Author: xiongrencong
Author-email: xiongrencong@youcheyihou.com
License: UNKNOWN
Platform: UNKNOWN
